silverweasel/__init__.py
silverweasel/client.py
silverweasel/sftp.py
silverweasel/utils.py
silverweasel/data/ListMgmt-UserActions.xsd
silverweasel/data/Reporting1.xsd
silverweasel/tests/__init__.py
silverweasel/tests/test_linting.py
silverweasel/tests/test_utils.py
silverweasel-0.0.12.dist-info/LICENSE
silverweasel-0.0.12.dist-info/METADATA
silverweasel-0.0.12.dist-info/WHEEL
silverweasel-0.0.12.dist-info/top_level.txt
silverweasel-0.0.12.dist-info/RECORD
