Metadata-Version: 2.1
Name: silverweasel
Version: 0.0.12
Summary: Silverweasel is a library for dealing with the IBM Silverpop API
Home-page: http://github.com/theatlantic/silverweasel
Author: Brian Muller
Author-email: bamuller@gmail.com
License: MIT
Platform: UNKNOWN
Requires-Python: >=3
Requires-Dist: zeep (==2.4.0)
Requires-Dist: arrow (==0.12.1)
Requires-Dist: paramiko (==2.4.2)
